kinto_ldap/__init__.py
kinto_ldap/authentication.py
kinto_ldap/tests/__init__.py
kinto_ldap/tests/test_authentication.py
kinto_ldap/tests/test_includeme.py
kinto_ldap/tests/test_views.py
kinto_ldap-0.3.1.dist-info/DESCRIPTION.rst
kinto_ldap-0.3.1.dist-info/METADATA
kinto_ldap-0.3.1.dist-info/RECORD
kinto_ldap-0.3.1.dist-info/WHEEL
kinto_ldap-0.3.1.dist-info/metadata.json
kinto_ldap-0.3.1.dist-info/top_level.txt
